LICENSE
MANIFEST.in
README.md
pyproject.toml
setup.py
src/conette/__init__.py
src/conette/info.py
src/conette/predict.py
src/conette/prepare.py
src/conette/train.py
src/conette.egg-info/PKG-INFO
src/conette.egg-info/SOURCES.txt
src/conette.egg-info/dependency_links.txt
src/conette.egg-info/entry_points.txt
src/conette.egg-info/requires.txt
src/conette.egg-info/top_level.txt
src/conette/callbacks/__init__.py
src/conette/callbacks/aac_evaluator.py
src/conette/callbacks/aac_validator.py
src/conette/callbacks/custom_ckpt.py
src/conette/callbacks/debug.py
src/conette/callbacks/deepspeed.py
src/conette/callbacks/log.py
src/conette/callbacks/resume.py
src/conette/callbacks/stats_saver.py
src/conette/callbacks/time.py
src/conette/datamodules/__init__.py
src/conette/datamodules/aac_dm.py
src/conette/datamodules/collate.py
src/conette/datamodules/common.py
src/conette/datamodules/hdf.py
src/conette/datasets/__init__.py
src/conette/datasets/typing.py
src/conette/datasets/utils.py
src/conette/huggingface/__init__.py
src/conette/huggingface/config.py
src/conette/huggingface/model.py
src/conette/huggingface/preprocessor.py
src/conette/huggingface/setup.py
src/conette/metrics/__init__.py
src/conette/metrics/cross_referencing.py
src/conette/metrics/classes/__init__.py
src/conette/metrics/classes/all_metrics.py
src/conette/metrics/classes/diversity.py
src/conette/metrics/classes/new_words.py
src/conette/metrics/classes/text_stats.py
src/conette/metrics/functional/__init__.py
src/conette/metrics/functional/diversity.py
src/conette/metrics/functional/new_words.py
src/conette/metrics/functional/text_stats.py
src/conette/nn/__init__.py
src/conette/nn/ckpt.py
src/conette/nn/decoders/__init__.py
src/conette/nn/decoders/aac_tfmer.py
src/conette/nn/decoding/__init__.py
src/conette/nn/decoding/beam.py
src/conette/nn/decoding/common.py
src/conette/nn/decoding/forcing.py
src/conette/nn/decoding/greedy.py
src/conette/nn/encoders/__init__.py
src/conette/nn/encoders/cnn10.py
src/conette/nn/encoders/cnn14.py
src/conette/nn/encoders/cnn14_decisionlevel_att.py
src/conette/nn/encoders/convnext.py
src/conette/nn/encoders/ident.py
src/conette/nn/functional/__init__.py
src/conette/nn/functional/drop.py
